policy_inspector/__init__.py
policy_inspector/__main__.py
policy_inspector/cli.py
policy_inspector/config.py
policy_inspector/example/1/address_groups.json
policy_inspector/example/1/address_objects.json
policy_inspector/example/1/config.yaml
policy_inspector/example/1/policies.json
policy_inspector/example/2/address_groups.json
policy_inspector/example/2/address_objects.json
policy_inspector/example/2/config.yaml
policy_inspector/example/2/policies.json
policy_inspector/example/3/address_groups.json
policy_inspector/example/3/address_objects.json
policy_inspector/example/3/config.yaml
policy_inspector/example/3/policies.json
policy_inspector/filters.py
policy_inspector/mock_panorama.py
policy_inspector/model/__init__.py
policy_inspector/model/address_group.py
policy_inspector/model/address_object.py
policy_inspector/model/base.py
policy_inspector/model/security_rule.py
policy_inspector/panorama.py
policy_inspector/resolver.py
policy_inspector/scenario.py
policy_inspector/scenarios/__init__.py
policy_inspector/scenarios/address_match/base.py
policy_inspector/scenarios/shadowing/__init__.py
policy_inspector/scenarios/shadowing/advanced.py
policy_inspector/scenarios/shadowing/checks.py
policy_inspector/scenarios/shadowing/export.py
policy_inspector/scenarios/shadowing/report_template.html
policy_inspector/scenarios/shadowing/show.py
policy_inspector/scenarios/shadowing/simple.py
policy_inspector/utils.py
policy_inspector-0.2.1.dist-info/LICENSE
policy_inspector-0.2.1.dist-info/METADATA
policy_inspector-0.2.1.dist-info/WHEEL
policy_inspector-0.2.1.dist-info/entry_points.txt
policy_inspector-0.2.1.dist-info/RECORD
